{
  "stage": "12.20A",
  "name": "source_anchor_inspection_before_bounded_continuous_streaming_patch",
  "timestamp": "2026-06-03T17:04:57",
  "source": "/home/zanshi/robot-mpc-wbc-locomotion/ros2_ws/src/robot_mpc_wbc_cpp_controller/src/disabled_controller_node.cpp",
  "source_exists": true,
  "pass": true,
  "fail_reasons": [],
  "anchors": {
    "publish_hits": [
      {
        "line": 319,
        "pattern": "->publish\\s*\\(",
        "text": "    active_torque_cmd_publisher_->publish(msg);"
      }
    ],
    "timer_hits": [
      {
        "line": 36,
        "pattern": "create_wall_timer",
        "text": "    stage1214_one_shot_publish_timer_ = this->create_wall_timer("
      },
      {
        "line": 36,
        "pattern": "timer_",
        "text": "    stage1214_one_shot_publish_timer_ = this->create_wall_timer("
      },
      {
        "line": 36,
        "pattern": "one_shot",
        "text": "    stage1214_one_shot_publish_timer_ = this->create_wall_timer("
      },
      {
        "line": 39,
        "pattern": "timer_",
        "text": "        if (stage1214_one_shot_publish_timer_) {"
      },
      {
        "line": 39,
        "pattern": "one_shot",
        "text": "        if (stage1214_one_shot_publish_timer_) {"
      },
      {
        "line": 40,
        "pattern": "timer_",
        "text": "          stage1214_one_shot_publish_timer_->cancel();"
      },
      {
        "line": 40,
        "pattern": "one_shot",
        "text": "          stage1214_one_shot_publish_timer_->cancel();"
      },
      {
        "line": 40,
        "pattern": "cancel\\s*\\(",
        "text": "          stage1214_one_shot_publish_timer_->cancel();"
      },
      {
        "line": 134,
        "pattern": "create_wall_timer",
        "text": "    status_timer_ = create_wall_timer("
      },
      {
        "line": 134,
        "pattern": "timer_",
        "text": "    status_timer_ = create_wall_timer("
      },
      {
        "line": 252,
        "pattern": "timer_",
        "text": "  rclcpp::TimerBase::SharedPtr status_timer_;"
      },
      {
        "line": 323,
        "pattern": "timer_",
        "text": "  rclcpp::TimerBase::SharedPtr stage1214_one_shot_publish_timer_;"
      },
      {
        "line": 323,
        "pattern": "one_shot",
        "text": "  rclcpp::TimerBase::SharedPtr stage1214_one_shot_publish_timer_;"
      }
    ],
    "param_hits": [
      {
        "line": 25,
        "pattern": "declare_parameter",
        "text": "    declare_parameter<bool>(\"enable_torque_publisher\", false);"
      },
      {
        "line": 25,
        "pattern": "enable_torque_publisher",
        "text": "    declare_parameter<bool>(\"enable_torque_publisher\", false);"
      },
      {
        "line": 26,
        "pattern": "declare_parameter",
        "text": "    declare_parameter<bool>(\"confirm_torque_publisher_enable\", false);"
      },
      {
        "line": 26,
        "pattern": "confirm_torque_publisher_enable",
        "text": "    declare_parameter<bool>(\"confirm_torque_publisher_enable\", false);"
      },
      {
        "line": 43,
        "pattern": "get_parameter",
        "text": "          this->get_parameter(\"enable_torque_publisher\").as_bool();"
      },
      {
        "line": 43,
        "pattern": "enable_torque_publisher",
        "text": "          this->get_parameter(\"enable_torque_publisher\").as_bool();"
      },
      {
        "line": 45,
        "pattern": "get_parameter",
        "text": "          this->get_parameter(\"confirm_torque_publisher_enable\").as_bool();"
      },
      {
        "line": 45,
        "pattern": "confirm_torque_publisher_enable",
        "text": "          this->get_parameter(\"confirm_torque_publisher_enable\").as_bool();"
      },
      {
        "line": 155,
        "pattern": "enable_torque_publisher",
        "text": "          \"disabled controller skeleton: state_ready=%d inputs_fresh=%d internal_safe_tau_size=%zu dormant_payload_size=%zu internal_safe_tau_max_abs=%.6f clamp_applied=%d enable_torque_publisher=%d confirm_torque_publisher_enable=%d manual_enable_active=%d dormant_publisher_path_skeleton_present=%d dormant_construct_allowed=%d dormant_publish_allowed=%d torque_publisher_enabled=0 uses_safety_utilities=1\","
      },
      {
        "line": 155,
        "pattern": "confirm_torque_publisher_enable",
        "text": "          \"disabled controller skeleton: state_ready=%d inputs_fresh=%d internal_safe_tau_size=%zu dormant_payload_size=%zu internal_safe_tau_max_abs=%.6f clamp_applied=%d enable_torque_publisher=%d confirm_torque_publisher_enable=%d manual_enable_active=%d dormant_publisher_path_skeleton_present=%d dormant_construct_allowed=%d dormant_publish_allowed=%d torque_publisher_enabled=0 uses_safety_utilities=1\","
      },
      {
        "line": 162,
        "pattern": "enable_torque_publisher",
        "text": "          enable_torque_publisher_param_,"
      },
      {
        "line": 163,
        "pattern": "confirm_torque_publisher_enable",
        "text": "          confirm_torque_publisher_enable_param_,"
      },
      {
        "line": 185,
        "pattern": "enable_torque_publisher",
        "text": "    enable_torque_publisher_param_ ="
      },
      {
        "line": 186,
        "pattern": "get_parameter",
        "text": "      get_parameter(\"enable_torque_publisher\").as_bool();"
      },
      {
        "line": 186,
        "pattern": "enable_torque_publisher",
        "text": "      get_parameter(\"enable_torque_publisher\").as_bool();"
      },
      {
        "line": 188,
        "pattern": "confirm_torque_publisher_enable",
        "text": "    confirm_torque_publisher_enable_param_ ="
      },
      {
        "line": 189,
        "pattern": "get_parameter",
        "text": "      get_parameter(\"confirm_torque_publisher_enable\").as_bool();"
      },
      {
        "line": 189,
        "pattern": "confirm_torque_publisher_enable",
        "text": "      get_parameter(\"confirm_torque_publisher_enable\").as_bool();"
      },
      {
        "line": 192,
        "pattern": "enable_torque_publisher",
        "text": "      enable_torque_publisher_param_ &&"
      },
      {
        "line": 193,
        "pattern": "confirm_torque_publisher_enable",
        "text": "      confirm_torque_publisher_enable_param_;"
      },
      {
        "line": 261,
        "pattern": "enable_torque_publisher",
        "text": "  bool enable_torque_publisher_param_ = false;"
      },
      {
        "line": 262,
        "pattern": "confirm_torque_publisher_enable",
        "text": "  bool confirm_torque_publisher_enable_param_ = false;"
      }
    ],
    "helper_hits": [
      {
        "line": 17,
        "pattern": "safe",
        "text": "#include \"robot_mpc_wbc_cpp_controller/torque_safety.hpp\""
      },
      {
        "line": 18,
        "pattern": "zero",
        "text": "#include \"robot_mpc_wbc_cpp_controller/zero_torque_dry_run.hpp\""
      },
      {
        "line": 25,
        "pattern": "publish",
        "text": "    declare_parameter<bool>(\"enable_torque_publisher\", false);"
      },
      {
        "line": 26,
        "pattern": "publish",
        "text": "    declare_parameter<bool>(\"confirm_torque_publisher_enable\", false);"
      },
      {
        "line": 28,
        "pattern": "publish",
        "text": "    active_torque_cmd_publisher_ ="
      },
      {
        "line": 29,
        "pattern": "Float64MultiArray",
        "text": "      this->create_publisher<std_msgs::msg::Float64MultiArray>("
      },
      {
        "line": 29,
        "pattern": "publish",
        "text": "      this->create_publisher<std_msgs::msg::Float64MultiArray>("
      },
      {
        "line": 30,
        "pattern": "joint_torque_cmd",
        "text": "        \"/go1/joint_torque_cmd\", rclcpp::QoS(1));"
      },
      {
        "line": 33,
        "pattern": "publish",
        "text": "      \"Stage 12.4 active torque publisher constructed without publish call; manual flags remain default false.\");"
      },
      {
        "line": 36,
        "pattern": "publish",
        "text": "    stage1214_one_shot_publish_timer_ = this->create_wall_timer("
      },
      {
        "line": 39,
        "pattern": "publish",
        "text": "        if (stage1214_one_shot_publish_timer_) {"
      },
      {
        "line": 40,
        "pattern": "publish",
        "text": "          stage1214_one_shot_publish_timer_->cancel();"
      },
      {
        "line": 43,
        "pattern": "publish",
        "text": "          this->get_parameter(\"enable_torque_publisher\").as_bool();"
      },
      {
        "line": 45,
        "pattern": "publish",
        "text": "          this->get_parameter(\"confirm_torque_publisher_enable\").as_bool();"
      },
      {
        "line": 47,
        "pattern": "bounded",
        "text": "        stage1214_bounded_publish_invoked_ ="
      },
      {
        "line": 47,
        "pattern": "publish",
        "text": "        stage1214_bounded_publish_invoked_ ="
      },
      {
        "line": 48,
        "pattern": "publish",
        "text": "          publishBoundedZeroSafeTorqueOnceIfAllowed("
      },
      {
        "line": 52,
        "pattern": "zero",
        "text": "    zero_torque_dry_run_ = robot_mpc_wbc_cpp_controller::makeZeroTorqueDryRun();"
      },
      {
        "line": 53,
        "pattern": "safe",
        "text": "    safe_torque_dry_run_ = robot_mpc_wbc_cpp_controller::makeZeroTorqueDryRun();"
      },
      {
        "line": 78,
        "pattern": "Float64MultiArray",
        "text": "    base_state_sub_ = create_subscription<std_msgs::msg::Float64MultiArray>("
      },
      {
        "line": 81,
        "pattern": "Float64MultiArray",
        "text": "      [this](std_msgs::msg::Float64MultiArray::SharedPtr msg) {"
      },
      {
        "line": 149,
        "pattern": "publish",
        "text": "        const bool publish_allowed = dormantPublishAllowed(state_ready);"
      },
      {
        "line": 155,
        "pattern": "safe",
        "text": "          \"disabled controller skeleton: state_ready=%d inputs_fresh=%d internal_safe_tau_size=%zu dormant_payload_size=%zu internal_safe_tau_max_abs=%.6f clamp_applied=%d enable_torque_publisher=%d confirm_torque_publisher_enable=%d manual_enable_active=%d dormant_publisher_path_skeleton_present=%d dormant_construct_allowed=%d dormant_publish_allowed=%d torque_publisher_enabled=0 uses_safety_utilities=1\","
      },
      {
        "line": 155,
        "pattern": "publish",
        "text": "          \"disabled controller skeleton: state_ready=%d inputs_fresh=%d internal_safe_tau_size=%zu dormant_payload_size=%zu internal_safe_tau_max_abs=%.6f clamp_applied=%d enable_torque_publisher=%d confirm_torque_publisher_enable=%d manual_enable_active=%d dormant_publisher_path_skeleton_present=%d dormant_construct_allowed=%d dormant_publish_allowed=%d torque_publisher_enabled=0 uses_safety_utilities=1\","
      },
      {
        "line": 158,
        "pattern": "safe",
        "text": "          safe_torque_dry_run_.size(),"
      },
      {
        "line": 162,
        "pattern": "publish",
        "text": "          enable_torque_publisher_param_,"
      },
      {
        "line": 163,
        "pattern": "publish",
        "text": "          confirm_torque_publisher_enable_param_,"
      },
      {
        "line": 167,
        "pattern": "publish",
        "text": "          publish_allowed);"
      },
      {
        "line": 172,
        "pattern": "publish",
        "text": "      \"Go1 disabled C++ controller skeleton started with dormant publisher-path skeleton. No ROS torque publisher is constructed.\");"
      },
      {
        "line": 185,
        "pattern": "publish",
        "text": "    enable_torque_publisher_param_ ="
      },
      {
        "line": 186,
        "pattern": "publish",
        "text": "      get_parameter(\"enable_torque_publisher\").as_bool();"
      },
      {
        "line": 188,
        "pattern": "publish",
        "text": "    confirm_torque_publisher_enable_param_ ="
      },
      {
        "line": 189,
        "pattern": "publish",
        "text": "      get_parameter(\"confirm_torque_publisher_enable\").as_bool();"
      },
      {
        "line": 192,
        "pattern": "publish",
        "text": "      enable_torque_publisher_param_ &&"
      },
      {
        "line": 193,
        "pattern": "publish",
        "text": "      confirm_torque_publisher_enable_param_;"
      },
      {
        "line": 217,
        "pattern": "zero",
        "text": "        ? zero_torque_dry_run_"
      },
      {
        "line": 223,
        "pattern": "safe",
        "text": "    safe_torque_dry_run_ = last_clamp_result_.tau;"
      },
      {
        "line": 239,
        "pattern": "Float64MultiArray",
        "text": "  std_msgs::msg::Float64MultiArray makeDormantSafeTorqueCommandMessage() const {"
      },
      {
        "line": 240,
        "pattern": "Float64MultiArray",
        "text": "    std_msgs::msg::Float64MultiArray msg;"
      },
      {
        "line": 242,
        "pattern": "safe",
        "text": "    msg.data.assign(safe_torque_dry_run_.begin(), safe_torque_dry_run_.end());"
      },
      {
        "line": 247,
        "pattern": "Float64MultiArray",
        "text": "  rclcpp::Subscription<std_msgs::msg::Float64MultiArray>::SharedPtr base_state_sub_;"
      },
      {
        "line": 261,
        "pattern": "publish",
        "text": "  bool enable_torque_publisher_param_ = false;"
      },
      {
        "line": 262,
        "pattern": "publish",
        "text": "  bool confirm_torque_publisher_enable_param_ = false;"
      },
      {
        "line": 280,
        "pattern": "zero",
        "text": "  robot_mpc_wbc_cpp_controller::TorqueVector zero_torque_dry_run_{};"
      },
      {
        "line": 281,
        "pattern": "safe",
        "text": "  robot_mpc_wbc_cpp_controller::TorqueVector safe_torque_dry_run_{};"
      },
      {
        "line": 285,
        "pattern": "Float64MultiArray",
        "text": "  rclcpp::Publisher<std_msgs::msg::Float64MultiArray>::SharedPtr active_torque_cmd_publisher_;"
      },
      {
        "line": 285,
        "pattern": "publish",
        "text": "  rclcpp::Publisher<std_msgs::msg::Float64MultiArray>::SharedPtr active_torque_cmd_publisher_;"
      },
      {
        "line": 290,
        "pattern": "Float64MultiArray",
        "text": "  std_msgs::msg::Float64MultiArray makeStage1214ZeroSafeTorqueCommandMessage() const"
      },
      {
        "line": 292,
        "pattern": "Float64MultiArray",
        "text": "    std_msgs::msg::Float64MultiArray msg;"
      },
      {
        "line": 297,
        "pattern": "publish",
        "text": "  bool publishBoundedZeroSafeTorqueOnceIfAllowed("
      },
      {
        "line": 305,
        "pattern": "publish",
        "text": "    if (active_torque_cmd_publisher_ == nullptr) {"
      },
      {
        "line": 319,
        "pattern": "publish",
        "text": "    active_torque_cmd_publisher_->publish(msg);"
      },
      {
        "line": 323,
        "pattern": "publish",
        "text": "  rclcpp::TimerBase::SharedPtr stage1214_one_shot_publish_timer_;"
      },
      {
        "line": 324,
        "pattern": "bounded",
        "text": "  bool stage1214_bounded_publish_invoked_{false};"
      },
      {
        "line": 324,
        "pattern": "publish",
        "text": "  bool stage1214_bounded_publish_invoked_{false};"
      }
    ],
    "continuous_hits": []
  },
  "contexts": {
    "publish_hits": [
      {
        "center_line": 319,
        "context": "0309:     auto msg = makeStage1214ZeroSafeTorqueCommandMessage();\n0310:     if (msg.data.size() != kDormantTorquePayloadLength) {\n0311:       return false;\n0312:     }\n0313:     for (const auto value : msg.data) {\n0314:       if (!std::isfinite(value)) {\n0315:         return false;\n0316:       }\n0317:     }\n0318: \n0319:     active_torque_cmd_publisher_->publish(msg);\n0320:     return true;\n0321:   }\n0322: \n0323:   rclcpp::TimerBase::SharedPtr stage1214_one_shot_publish_timer_;\n0324:   bool stage1214_bounded_publish_invoked_{false};\n0325:   static constexpr bool kStage1214BoundedPublishCallImplemented = true;\n0326:   static constexpr bool kStage1214ContinuousPublishImplemented = false;\n0327: };\n0328: \n0329: int main(int argc, char ** argv) {"
      }
    ],
    "timer_hits": [
      {
        "center_line": 36,
        "context": "0026:     declare_parameter<bool>(\"confirm_torque_publisher_enable\", false);\n0027: \n0028:     active_torque_cmd_publisher_ =\n0029:       this->create_publisher<std_msgs::msg::Float64MultiArray>(\n0030:         \"/go1/joint_torque_cmd\", rclcpp::QoS(1));\n0031:     RCLCPP_INFO(\n0032:       this->get_logger(),\n0033:       \"Stage 12.4 active torque publisher constructed without publish call; manual flags remain default false.\");\n0034: \n0035: \n0036:     stage1214_one_shot_publish_timer_ = this->create_wall_timer(\n0037:       std::chrono::milliseconds(2500),\n0038:       [this]() {\n0039:         if (stage1214_one_shot_publish_timer_) {\n0040:           stage1214_one_shot_publish_timer_->cancel();\n0041:         }\n0042:         const bool stage1214_enable =\n0043:           this->get_parameter(\"enable_torque_publisher\").as_bool();\n0044:         const bool stage1214_confirm =\n0045:           this->get_parameter(\"confirm_torque_publisher_enable\").as_bool();\n0046:         const bool stage1214_state_ready = true;"
      },
      {
        "center_line": 36,
        "context": "0026:     declare_parameter<bool>(\"confirm_torque_publisher_enable\", false);\n0027: \n0028:     active_torque_cmd_publisher_ =\n0029:       this->create_publisher<std_msgs::msg::Float64MultiArray>(\n0030:         \"/go1/joint_torque_cmd\", rclcpp::QoS(1));\n0031:     RCLCPP_INFO(\n0032:       this->get_logger(),\n0033:       \"Stage 12.4 active torque publisher constructed without publish call; manual flags remain default false.\");\n0034: \n0035: \n0036:     stage1214_one_shot_publish_timer_ = this->create_wall_timer(\n0037:       std::chrono::milliseconds(2500),\n0038:       [this]() {\n0039:         if (stage1214_one_shot_publish_timer_) {\n0040:           stage1214_one_shot_publish_timer_->cancel();\n0041:         }\n0042:         const bool stage1214_enable =\n0043:           this->get_parameter(\"enable_torque_publisher\").as_bool();\n0044:         const bool stage1214_confirm =\n0045:           this->get_parameter(\"confirm_torque_publisher_enable\").as_bool();\n0046:         const bool stage1214_state_ready = true;"
      },
      {
        "center_line": 36,
        "context": "0026:     declare_parameter<bool>(\"confirm_torque_publisher_enable\", false);\n0027: \n0028:     active_torque_cmd_publisher_ =\n0029:       this->create_publisher<std_msgs::msg::Float64MultiArray>(\n0030:         \"/go1/joint_torque_cmd\", rclcpp::QoS(1));\n0031:     RCLCPP_INFO(\n0032:       this->get_logger(),\n0033:       \"Stage 12.4 active torque publisher constructed without publish call; manual flags remain default false.\");\n0034: \n0035: \n0036:     stage1214_one_shot_publish_timer_ = this->create_wall_timer(\n0037:       std::chrono::milliseconds(2500),\n0038:       [this]() {\n0039:         if (stage1214_one_shot_publish_timer_) {\n0040:           stage1214_one_shot_publish_timer_->cancel();\n0041:         }\n0042:         const bool stage1214_enable =\n0043:           this->get_parameter(\"enable_torque_publisher\").as_bool();\n0044:         const bool stage1214_confirm =\n0045:           this->get_parameter(\"confirm_torque_publisher_enable\").as_bool();\n0046:         const bool stage1214_state_ready = true;"
      },
      {
        "center_line": 39,
        "context": "0029:       this->create_publisher<std_msgs::msg::Float64MultiArray>(\n0030:         \"/go1/joint_torque_cmd\", rclcpp::QoS(1));\n0031:     RCLCPP_INFO(\n0032:       this->get_logger(),\n0033:       \"Stage 12.4 active torque publisher constructed without publish call; manual flags remain default false.\");\n0034: \n0035: \n0036:     stage1214_one_shot_publish_timer_ = this->create_wall_timer(\n0037:       std::chrono::milliseconds(2500),\n0038:       [this]() {\n0039:         if (stage1214_one_shot_publish_timer_) {\n0040:           stage1214_one_shot_publish_timer_->cancel();\n0041:         }\n0042:         const bool stage1214_enable =\n0043:           this->get_parameter(\"enable_torque_publisher\").as_bool();\n0044:         const bool stage1214_confirm =\n0045:           this->get_parameter(\"confirm_torque_publisher_enable\").as_bool();\n0046:         const bool stage1214_state_ready = true;\n0047:         stage1214_bounded_publish_invoked_ =\n0048:           publishBoundedZeroSafeTorqueOnceIfAllowed(\n0049:             stage1214_enable, stage1214_confirm, stage1214_state_ready);"
      },
      {
        "center_line": 39,
        "context": "0029:       this->create_publisher<std_msgs::msg::Float64MultiArray>(\n0030:         \"/go1/joint_torque_cmd\", rclcpp::QoS(1));\n0031:     RCLCPP_INFO(\n0032:       this->get_logger(),\n0033:       \"Stage 12.4 active torque publisher constructed without publish call; manual flags remain default false.\");\n0034: \n0035: \n0036:     stage1214_one_shot_publish_timer_ = this->create_wall_timer(\n0037:       std::chrono::milliseconds(2500),\n0038:       [this]() {\n0039:         if (stage1214_one_shot_publish_timer_) {\n0040:           stage1214_one_shot_publish_timer_->cancel();\n0041:         }\n0042:         const bool stage1214_enable =\n0043:           this->get_parameter(\"enable_torque_publisher\").as_bool();\n0044:         const bool stage1214_confirm =\n0045:           this->get_parameter(\"confirm_torque_publisher_enable\").as_bool();\n0046:         const bool stage1214_state_ready = true;\n0047:         stage1214_bounded_publish_invoked_ =\n0048:           publishBoundedZeroSafeTorqueOnceIfAllowed(\n0049:             stage1214_enable, stage1214_confirm, stage1214_state_ready);"
      },
      {
        "center_line": 40,
        "context": "0030:         \"/go1/joint_torque_cmd\", rclcpp::QoS(1));\n0031:     RCLCPP_INFO(\n0032:       this->get_logger(),\n0033:       \"Stage 12.4 active torque publisher constructed without publish call; manual flags remain default false.\");\n0034: \n0035: \n0036:     stage1214_one_shot_publish_timer_ = this->create_wall_timer(\n0037:       std::chrono::milliseconds(2500),\n0038:       [this]() {\n0039:         if (stage1214_one_shot_publish_timer_) {\n0040:           stage1214_one_shot_publish_timer_->cancel();\n0041:         }\n0042:         const bool stage1214_enable =\n0043:           this->get_parameter(\"enable_torque_publisher\").as_bool();\n0044:         const bool stage1214_confirm =\n0045:           this->get_parameter(\"confirm_torque_publisher_enable\").as_bool();\n0046:         const bool stage1214_state_ready = true;\n0047:         stage1214_bounded_publish_invoked_ =\n0048:           publishBoundedZeroSafeTorqueOnceIfAllowed(\n0049:             stage1214_enable, stage1214_confirm, stage1214_state_ready);\n0050:       });"
      },
      {
        "center_line": 40,
        "context": "0030:         \"/go1/joint_torque_cmd\", rclcpp::QoS(1));\n0031:     RCLCPP_INFO(\n0032:       this->get_logger(),\n0033:       \"Stage 12.4 active torque publisher constructed without publish call; manual flags remain default false.\");\n0034: \n0035: \n0036:     stage1214_one_shot_publish_timer_ = this->create_wall_timer(\n0037:       std::chrono::milliseconds(2500),\n0038:       [this]() {\n0039:         if (stage1214_one_shot_publish_timer_) {\n0040:           stage1214_one_shot_publish_timer_->cancel();\n0041:         }\n0042:         const bool stage1214_enable =\n0043:           this->get_parameter(\"enable_torque_publisher\").as_bool();\n0044:         const bool stage1214_confirm =\n0045:           this->get_parameter(\"confirm_torque_publisher_enable\").as_bool();\n0046:         const bool stage1214_state_ready = true;\n0047:         stage1214_bounded_publish_invoked_ =\n0048:           publishBoundedZeroSafeTorqueOnceIfAllowed(\n0049:             stage1214_enable, stage1214_confirm, stage1214_state_ready);\n0050:       });"
      },
      {
        "center_line": 40,
        "context": "0030:         \"/go1/joint_torque_cmd\", rclcpp::QoS(1));\n0031:     RCLCPP_INFO(\n0032:       this->get_logger(),\n0033:       \"Stage 12.4 active torque publisher constructed without publish call; manual flags remain default false.\");\n0034: \n0035: \n0036:     stage1214_one_shot_publish_timer_ = this->create_wall_timer(\n0037:       std::chrono::milliseconds(2500),\n0038:       [this]() {\n0039:         if (stage1214_one_shot_publish_timer_) {\n0040:           stage1214_one_shot_publish_timer_->cancel();\n0041:         }\n0042:         const bool stage1214_enable =\n0043:           this->get_parameter(\"enable_torque_publisher\").as_bool();\n0044:         const bool stage1214_confirm =\n0045:           this->get_parameter(\"confirm_torque_publisher_enable\").as_bool();\n0046:         const bool stage1214_state_ready = true;\n0047:         stage1214_bounded_publish_invoked_ =\n0048:           publishBoundedZeroSafeTorqueOnceIfAllowed(\n0049:             stage1214_enable, stage1214_confirm, stage1214_state_ready);\n0050:       });"
      }
    ],
    "param_hits": [
      {
        "center_line": 25,
        "context": "0015: #include \"std_msgs/msg/int32_multi_array.hpp\"\n0016: \n0017: #include \"robot_mpc_wbc_cpp_controller/torque_safety.hpp\"\n0018: #include \"robot_mpc_wbc_cpp_controller/zero_torque_dry_run.hpp\"\n0019: \n0020: using namespace std::chrono_literals;\n0021: \n0022: class Go1DisabledControllerNode final : public rclcpp::Node {\n0023: public:\n0024:   Go1DisabledControllerNode() : Node(\"go1_disabled_controller_node\") {\n0025:     declare_parameter<bool>(\"enable_torque_publisher\", false);\n0026:     declare_parameter<bool>(\"confirm_torque_publisher_enable\", false);\n0027: \n0028:     active_torque_cmd_publisher_ =\n0029:       this->create_publisher<std_msgs::msg::Float64MultiArray>(\n0030:         \"/go1/joint_torque_cmd\", rclcpp::QoS(1));\n0031:     RCLCPP_INFO(\n0032:       this->get_logger(),\n0033:       \"Stage 12.4 active torque publisher constructed without publish call; manual flags remain default false.\");\n0034: \n0035: "
      },
      {
        "center_line": 25,
        "context": "0015: #include \"std_msgs/msg/int32_multi_array.hpp\"\n0016: \n0017: #include \"robot_mpc_wbc_cpp_controller/torque_safety.hpp\"\n0018: #include \"robot_mpc_wbc_cpp_controller/zero_torque_dry_run.hpp\"\n0019: \n0020: using namespace std::chrono_literals;\n0021: \n0022: class Go1DisabledControllerNode final : public rclcpp::Node {\n0023: public:\n0024:   Go1DisabledControllerNode() : Node(\"go1_disabled_controller_node\") {\n0025:     declare_parameter<bool>(\"enable_torque_publisher\", false);\n0026:     declare_parameter<bool>(\"confirm_torque_publisher_enable\", false);\n0027: \n0028:     active_torque_cmd_publisher_ =\n0029:       this->create_publisher<std_msgs::msg::Float64MultiArray>(\n0030:         \"/go1/joint_torque_cmd\", rclcpp::QoS(1));\n0031:     RCLCPP_INFO(\n0032:       this->get_logger(),\n0033:       \"Stage 12.4 active torque publisher constructed without publish call; manual flags remain default false.\");\n0034: \n0035: "
      },
      {
        "center_line": 26,
        "context": "0016: \n0017: #include \"robot_mpc_wbc_cpp_controller/torque_safety.hpp\"\n0018: #include \"robot_mpc_wbc_cpp_controller/zero_torque_dry_run.hpp\"\n0019: \n0020: using namespace std::chrono_literals;\n0021: \n0022: class Go1DisabledControllerNode final : public rclcpp::Node {\n0023: public:\n0024:   Go1DisabledControllerNode() : Node(\"go1_disabled_controller_node\") {\n0025:     declare_parameter<bool>(\"enable_torque_publisher\", false);\n0026:     declare_parameter<bool>(\"confirm_torque_publisher_enable\", false);\n0027: \n0028:     active_torque_cmd_publisher_ =\n0029:       this->create_publisher<std_msgs::msg::Float64MultiArray>(\n0030:         \"/go1/joint_torque_cmd\", rclcpp::QoS(1));\n0031:     RCLCPP_INFO(\n0032:       this->get_logger(),\n0033:       \"Stage 12.4 active torque publisher constructed without publish call; manual flags remain default false.\");\n0034: \n0035: \n0036:     stage1214_one_shot_publish_timer_ = this->create_wall_timer("
      },
      {
        "center_line": 26,
        "context": "0016: \n0017: #include \"robot_mpc_wbc_cpp_controller/torque_safety.hpp\"\n0018: #include \"robot_mpc_wbc_cpp_controller/zero_torque_dry_run.hpp\"\n0019: \n0020: using namespace std::chrono_literals;\n0021: \n0022: class Go1DisabledControllerNode final : public rclcpp::Node {\n0023: public:\n0024:   Go1DisabledControllerNode() : Node(\"go1_disabled_controller_node\") {\n0025:     declare_parameter<bool>(\"enable_torque_publisher\", false);\n0026:     declare_parameter<bool>(\"confirm_torque_publisher_enable\", false);\n0027: \n0028:     active_torque_cmd_publisher_ =\n0029:       this->create_publisher<std_msgs::msg::Float64MultiArray>(\n0030:         \"/go1/joint_torque_cmd\", rclcpp::QoS(1));\n0031:     RCLCPP_INFO(\n0032:       this->get_logger(),\n0033:       \"Stage 12.4 active torque publisher constructed without publish call; manual flags remain default false.\");\n0034: \n0035: \n0036:     stage1214_one_shot_publish_timer_ = this->create_wall_timer("
      },
      {
        "center_line": 43,
        "context": "0033:       \"Stage 12.4 active torque publisher constructed without publish call; manual flags remain default false.\");\n0034: \n0035: \n0036:     stage1214_one_shot_publish_timer_ = this->create_wall_timer(\n0037:       std::chrono::milliseconds(2500),\n0038:       [this]() {\n0039:         if (stage1214_one_shot_publish_timer_) {\n0040:           stage1214_one_shot_publish_timer_->cancel();\n0041:         }\n0042:         const bool stage1214_enable =\n0043:           this->get_parameter(\"enable_torque_publisher\").as_bool();\n0044:         const bool stage1214_confirm =\n0045:           this->get_parameter(\"confirm_torque_publisher_enable\").as_bool();\n0046:         const bool stage1214_state_ready = true;\n0047:         stage1214_bounded_publish_invoked_ =\n0048:           publishBoundedZeroSafeTorqueOnceIfAllowed(\n0049:             stage1214_enable, stage1214_confirm, stage1214_state_ready);\n0050:       });\n0051: \n0052:     zero_torque_dry_run_ = robot_mpc_wbc_cpp_controller::makeZeroTorqueDryRun();\n0053:     safe_torque_dry_run_ = robot_mpc_wbc_cpp_controller::makeZeroTorqueDryRun();"
      },
      {
        "center_line": 43,
        "context": "0033:       \"Stage 12.4 active torque publisher constructed without publish call; manual flags remain default false.\");\n0034: \n0035: \n0036:     stage1214_one_shot_publish_timer_ = this->create_wall_timer(\n0037:       std::chrono::milliseconds(2500),\n0038:       [this]() {\n0039:         if (stage1214_one_shot_publish_timer_) {\n0040:           stage1214_one_shot_publish_timer_->cancel();\n0041:         }\n0042:         const bool stage1214_enable =\n0043:           this->get_parameter(\"enable_torque_publisher\").as_bool();\n0044:         const bool stage1214_confirm =\n0045:           this->get_parameter(\"confirm_torque_publisher_enable\").as_bool();\n0046:         const bool stage1214_state_ready = true;\n0047:         stage1214_bounded_publish_invoked_ =\n0048:           publishBoundedZeroSafeTorqueOnceIfAllowed(\n0049:             stage1214_enable, stage1214_confirm, stage1214_state_ready);\n0050:       });\n0051: \n0052:     zero_torque_dry_run_ = robot_mpc_wbc_cpp_controller::makeZeroTorqueDryRun();\n0053:     safe_torque_dry_run_ = robot_mpc_wbc_cpp_controller::makeZeroTorqueDryRun();"
      },
      {
        "center_line": 45,
        "context": "0035: \n0036:     stage1214_one_shot_publish_timer_ = this->create_wall_timer(\n0037:       std::chrono::milliseconds(2500),\n0038:       [this]() {\n0039:         if (stage1214_one_shot_publish_timer_) {\n0040:           stage1214_one_shot_publish_timer_->cancel();\n0041:         }\n0042:         const bool stage1214_enable =\n0043:           this->get_parameter(\"enable_torque_publisher\").as_bool();\n0044:         const bool stage1214_confirm =\n0045:           this->get_parameter(\"confirm_torque_publisher_enable\").as_bool();\n0046:         const bool stage1214_state_ready = true;\n0047:         stage1214_bounded_publish_invoked_ =\n0048:           publishBoundedZeroSafeTorqueOnceIfAllowed(\n0049:             stage1214_enable, stage1214_confirm, stage1214_state_ready);\n0050:       });\n0051: \n0052:     zero_torque_dry_run_ = robot_mpc_wbc_cpp_controller::makeZeroTorqueDryRun();\n0053:     safe_torque_dry_run_ = robot_mpc_wbc_cpp_controller::makeZeroTorqueDryRun();\n0054:     torque_clamp_config_ = robot_mpc_wbc_cpp_controller::makeUniformTorqueClampConfig(10.0);\n0055: "
      },
      {
        "center_line": 45,
        "context": "0035: \n0036:     stage1214_one_shot_publish_timer_ = this->create_wall_timer(\n0037:       std::chrono::milliseconds(2500),\n0038:       [this]() {\n0039:         if (stage1214_one_shot_publish_timer_) {\n0040:           stage1214_one_shot_publish_timer_->cancel();\n0041:         }\n0042:         const bool stage1214_enable =\n0043:           this->get_parameter(\"enable_torque_publisher\").as_bool();\n0044:         const bool stage1214_confirm =\n0045:           this->get_parameter(\"confirm_torque_publisher_enable\").as_bool();\n0046:         const bool stage1214_state_ready = true;\n0047:         stage1214_bounded_publish_invoked_ =\n0048:           publishBoundedZeroSafeTorqueOnceIfAllowed(\n0049:             stage1214_enable, stage1214_confirm, stage1214_state_ready);\n0050:       });\n0051: \n0052:     zero_torque_dry_run_ = robot_mpc_wbc_cpp_controller::makeZeroTorqueDryRun();\n0053:     safe_torque_dry_run_ = robot_mpc_wbc_cpp_controller::makeZeroTorqueDryRun();\n0054:     torque_clamp_config_ = robot_mpc_wbc_cpp_controller::makeUniformTorqueClampConfig(10.0);\n0055: "
      }
    ],
    "helper_hits": [
      {
        "center_line": 17,
        "context": "0007: #include <string>\n0008: #include <vector>\n0009: \n0010: #include \"rclcpp/rclcpp.hpp\"\n0011: #include \"sensor_msgs/msg/imu.hpp\"\n0012: #include \"sensor_msgs/msg/joint_state.hpp\"\n0013: #include \"std_msgs/msg/float64.hpp\"\n0014: #include \"std_msgs/msg/float64_multi_array.hpp\"\n0015: #include \"std_msgs/msg/int32_multi_array.hpp\"\n0016: \n0017: #include \"robot_mpc_wbc_cpp_controller/torque_safety.hpp\"\n0018: #include \"robot_mpc_wbc_cpp_controller/zero_torque_dry_run.hpp\"\n0019: \n0020: using namespace std::chrono_literals;\n0021: \n0022: class Go1DisabledControllerNode final : public rclcpp::Node {\n0023: public:\n0024:   Go1DisabledControllerNode() : Node(\"go1_disabled_controller_node\") {\n0025:     declare_parameter<bool>(\"enable_torque_publisher\", false);\n0026:     declare_parameter<bool>(\"confirm_torque_publisher_enable\", false);\n0027: "
      },
      {
        "center_line": 18,
        "context": "0008: #include <vector>\n0009: \n0010: #include \"rclcpp/rclcpp.hpp\"\n0011: #include \"sensor_msgs/msg/imu.hpp\"\n0012: #include \"sensor_msgs/msg/joint_state.hpp\"\n0013: #include \"std_msgs/msg/float64.hpp\"\n0014: #include \"std_msgs/msg/float64_multi_array.hpp\"\n0015: #include \"std_msgs/msg/int32_multi_array.hpp\"\n0016: \n0017: #include \"robot_mpc_wbc_cpp_controller/torque_safety.hpp\"\n0018: #include \"robot_mpc_wbc_cpp_controller/zero_torque_dry_run.hpp\"\n0019: \n0020: using namespace std::chrono_literals;\n0021: \n0022: class Go1DisabledControllerNode final : public rclcpp::Node {\n0023: public:\n0024:   Go1DisabledControllerNode() : Node(\"go1_disabled_controller_node\") {\n0025:     declare_parameter<bool>(\"enable_torque_publisher\", false);\n0026:     declare_parameter<bool>(\"confirm_torque_publisher_enable\", false);\n0027: \n0028:     active_torque_cmd_publisher_ ="
      },
      {
        "center_line": 25,
        "context": "0015: #include \"std_msgs/msg/int32_multi_array.hpp\"\n0016: \n0017: #include \"robot_mpc_wbc_cpp_controller/torque_safety.hpp\"\n0018: #include \"robot_mpc_wbc_cpp_controller/zero_torque_dry_run.hpp\"\n0019: \n0020: using namespace std::chrono_literals;\n0021: \n0022: class Go1DisabledControllerNode final : public rclcpp::Node {\n0023: public:\n0024:   Go1DisabledControllerNode() : Node(\"go1_disabled_controller_node\") {\n0025:     declare_parameter<bool>(\"enable_torque_publisher\", false);\n0026:     declare_parameter<bool>(\"confirm_torque_publisher_enable\", false);\n0027: \n0028:     active_torque_cmd_publisher_ =\n0029:       this->create_publisher<std_msgs::msg::Float64MultiArray>(\n0030:         \"/go1/joint_torque_cmd\", rclcpp::QoS(1));\n0031:     RCLCPP_INFO(\n0032:       this->get_logger(),\n0033:       \"Stage 12.4 active torque publisher constructed without publish call; manual flags remain default false.\");\n0034: \n0035: "
      },
      {
        "center_line": 26,
        "context": "0016: \n0017: #include \"robot_mpc_wbc_cpp_controller/torque_safety.hpp\"\n0018: #include \"robot_mpc_wbc_cpp_controller/zero_torque_dry_run.hpp\"\n0019: \n0020: using namespace std::chrono_literals;\n0021: \n0022: class Go1DisabledControllerNode final : public rclcpp::Node {\n0023: public:\n0024:   Go1DisabledControllerNode() : Node(\"go1_disabled_controller_node\") {\n0025:     declare_parameter<bool>(\"enable_torque_publisher\", false);\n0026:     declare_parameter<bool>(\"confirm_torque_publisher_enable\", false);\n0027: \n0028:     active_torque_cmd_publisher_ =\n0029:       this->create_publisher<std_msgs::msg::Float64MultiArray>(\n0030:         \"/go1/joint_torque_cmd\", rclcpp::QoS(1));\n0031:     RCLCPP_INFO(\n0032:       this->get_logger(),\n0033:       \"Stage 12.4 active torque publisher constructed without publish call; manual flags remain default false.\");\n0034: \n0035: \n0036:     stage1214_one_shot_publish_timer_ = this->create_wall_timer("
      },
      {
        "center_line": 28,
        "context": "0018: #include \"robot_mpc_wbc_cpp_controller/zero_torque_dry_run.hpp\"\n0019: \n0020: using namespace std::chrono_literals;\n0021: \n0022: class Go1DisabledControllerNode final : public rclcpp::Node {\n0023: public:\n0024:   Go1DisabledControllerNode() : Node(\"go1_disabled_controller_node\") {\n0025:     declare_parameter<bool>(\"enable_torque_publisher\", false);\n0026:     declare_parameter<bool>(\"confirm_torque_publisher_enable\", false);\n0027: \n0028:     active_torque_cmd_publisher_ =\n0029:       this->create_publisher<std_msgs::msg::Float64MultiArray>(\n0030:         \"/go1/joint_torque_cmd\", rclcpp::QoS(1));\n0031:     RCLCPP_INFO(\n0032:       this->get_logger(),\n0033:       \"Stage 12.4 active torque publisher constructed without publish call; manual flags remain default false.\");\n0034: \n0035: \n0036:     stage1214_one_shot_publish_timer_ = this->create_wall_timer(\n0037:       std::chrono::milliseconds(2500),\n0038:       [this]() {"
      },
      {
        "center_line": 29,
        "context": "0019: \n0020: using namespace std::chrono_literals;\n0021: \n0022: class Go1DisabledControllerNode final : public rclcpp::Node {\n0023: public:\n0024:   Go1DisabledControllerNode() : Node(\"go1_disabled_controller_node\") {\n0025:     declare_parameter<bool>(\"enable_torque_publisher\", false);\n0026:     declare_parameter<bool>(\"confirm_torque_publisher_enable\", false);\n0027: \n0028:     active_torque_cmd_publisher_ =\n0029:       this->create_publisher<std_msgs::msg::Float64MultiArray>(\n0030:         \"/go1/joint_torque_cmd\", rclcpp::QoS(1));\n0031:     RCLCPP_INFO(\n0032:       this->get_logger(),\n0033:       \"Stage 12.4 active torque publisher constructed without publish call; manual flags remain default false.\");\n0034: \n0035: \n0036:     stage1214_one_shot_publish_timer_ = this->create_wall_timer(\n0037:       std::chrono::milliseconds(2500),\n0038:       [this]() {\n0039:         if (stage1214_one_shot_publish_timer_) {"
      },
      {
        "center_line": 29,
        "context": "0019: \n0020: using namespace std::chrono_literals;\n0021: \n0022: class Go1DisabledControllerNode final : public rclcpp::Node {\n0023: public:\n0024:   Go1DisabledControllerNode() : Node(\"go1_disabled_controller_node\") {\n0025:     declare_parameter<bool>(\"enable_torque_publisher\", false);\n0026:     declare_parameter<bool>(\"confirm_torque_publisher_enable\", false);\n0027: \n0028:     active_torque_cmd_publisher_ =\n0029:       this->create_publisher<std_msgs::msg::Float64MultiArray>(\n0030:         \"/go1/joint_torque_cmd\", rclcpp::QoS(1));\n0031:     RCLCPP_INFO(\n0032:       this->get_logger(),\n0033:       \"Stage 12.4 active torque publisher constructed without publish call; manual flags remain default false.\");\n0034: \n0035: \n0036:     stage1214_one_shot_publish_timer_ = this->create_wall_timer(\n0037:       std::chrono::milliseconds(2500),\n0038:       [this]() {\n0039:         if (stage1214_one_shot_publish_timer_) {"
      },
      {
        "center_line": 30,
        "context": "0020: using namespace std::chrono_literals;\n0021: \n0022: class Go1DisabledControllerNode final : public rclcpp::Node {\n0023: public:\n0024:   Go1DisabledControllerNode() : Node(\"go1_disabled_controller_node\") {\n0025:     declare_parameter<bool>(\"enable_torque_publisher\", false);\n0026:     declare_parameter<bool>(\"confirm_torque_publisher_enable\", false);\n0027: \n0028:     active_torque_cmd_publisher_ =\n0029:       this->create_publisher<std_msgs::msg::Float64MultiArray>(\n0030:         \"/go1/joint_torque_cmd\", rclcpp::QoS(1));\n0031:     RCLCPP_INFO(\n0032:       this->get_logger(),\n0033:       \"Stage 12.4 active torque publisher constructed without publish call; manual flags remain default false.\");\n0034: \n0035: \n0036:     stage1214_one_shot_publish_timer_ = this->create_wall_timer(\n0037:       std::chrono::milliseconds(2500),\n0038:       [this]() {\n0039:         if (stage1214_one_shot_publish_timer_) {\n0040:           stage1214_one_shot_publish_timer_->cancel();"
      }
    ],
    "continuous_hits": []
  },
  "source_hash": "1970e55723158545b775a707b99f4e5801f80d96f93cf1f3301f5e27aa15d3e6",
  "source_hash_matches_stage1219": true,
  "publish_call_count": 1,
  "has_existing_continuous_streaming_markers": false,
  "source_has_exactly_one_publish_call": true,
  "source_has_no_continuous_streaming_markers": true
}