{
  "stage": "13.2C",
  "name": "final_2400step_simulation_only_robustness_evidence_freeze",
  "timestamp": "2026-06-04T10:18:42",
  "pass": true,
  "fail_reasons": [],
  "simulation_only_project": true,
  "hardware_deployment_scope": "out_of_scope_by_user_constraint",
  "hardware_deployment_completed": false,
  "torque_enable_ready": false,
  "torque_publisher_enabled": false,
  "control_law_changed": false,
  "baseline_type": "mixed_online_control_baseline",
  "stage13_1b_1200step_pass": true,
  "stage13_2a_r2_derived_runner_pass": true,
  "stage13_2b_r1_2400step_pass": true,
  "mixed_2400_summary": {
    "wbc_script": "scripts/stage13_2_2400step_online_full_wbc_scheduler_runner.py",
    "swing_target_csv": "results/logs_sample/stage13_2_2400step_swing_trajectory_tracking_check.csv",
    "total_steps": 2400,
    "transition_count": 11,
    "trot_FR_RL_steps": 1200,
    "trot_FL_RR_steps": 1200,
    "stance_kp": 60,
    "stance_kd": 2,
    "swing_kp": 80,
    "swing_kd": 2,
    "stance_wbc_scale": 0.2,
    "swing_pd_scale": 1,
    "swing_target_scale": 0.35,
    "torque_limit": 23.7,
    "initial_z": 0.284805846483,
    "final_z": 0.286030728906,
    "min_z": 0.274552192756,
    "max_z": 0.293169864411,
    "delta_z": 0.001224882422,
    "final_roll": -0.000918501417,
    "final_pitch": -0.016903082043,
    "max_abs_roll": 0.056707402709,
    "roll_margin_to_0p20": 0.143292597291,
    "max_abs_pitch": 0.04832948253,
    "pitch_margin_to_0p20": 0.15167051747,
    "z_margin_to_0p22": 0.054552192756,
    "max_joint_error": 0.077233662573,
    "max_swing_joint_error": 0.051395902876,
    "max_stance_joint_error": 0.077233662573,
    "max_tau_stance_pd_abs": 11.083222358114,
    "max_tau_stance_wbc_abs": 2.125887056052,
    "max_tau_swing_pd_abs": 9.659563043535,
    "max_tau_total_raw_abs": 9.659563043535,
    "max_tau_total_abs": 9.659563043535,
    "max_cmd_step_jump_norm": 25.788963931985,
    "max_cmd_step_jump_abs": 11.568156828496,
    "max_dyn_res_norm": 7.732488454756e-08,
    "max_stance_acc_res_norm": 3.52089100597e-09,
    "max_swing_acc_error_norm": 0.2545718566371,
    "qp_fail_steps": 0,
    "saturation_steps": 0,
    "pass": true,
    "pass_margin": true
  },
  "wbc_2400_summary": {
    "scheduler": "phase_trot",
    "total_steps": 2400,
    "dt": 0.002,
    "period_steps": 400,
    "half_period_steps": 200,
    "trot_FR_RL_steps": 1200,
    "trot_FL_RR_steps": 1200,
    "transition_count": 11,
    "kp_posture": 60,
    "kd_posture": 2,
    "torque_limit": 23.7,
    "base_qdd_z_ref": 0.03,
    "swing_acc_ref_x": 0.1,
    "swing_acc_ref_y": 0,
    "swing_acc_ref_z": 0.2,
    "ramp_alpha": 0.15,
    "initial_z": 0.284805846483,
    "final_z": 0.304968764218,
    "min_z": 0.284525843843,
    "max_z": 0.325211798729,
    "delta_z": 0.020162917735,
    "final_roll": 0.116402583877,
    "final_pitch": 0.060223800924,
    "max_abs_roll": 0.163118252883,
    "roll_margin_to_limit": 0.036881747117,
    "max_abs_pitch": 0.106881861177,
    "pitch_margin_to_limit": 0.093118138823,
    "z_margin_to_limit": 0.064525843843,
    "max_tau_pd_abs": 17.914484841257,
    "max_tau_wbc_abs": 10.722716789116,
    "max_tau_total_abs": 11.520998707973,
    "max_cmd_step_jump_norm": 3.444357031147,
    "max_cmd_step_jump_abs": 1.782238605127,
    "max_dyn_res_norm": 1.072235565455e-07,
    "max_stance_acc_res_norm": 4.121509819804e-09,
    "max_swing_acc_error_norm": 0.6846131992978,
    "qp_fail_steps": 0,
    "saturation_steps": 0,
    "pass": true,
    "pass_margin": true
  },
  "required_checks": {
    "simulation_only_project": true,
    "hardware_scope_out_of_scope": true,
    "hardware_deployment_completed_false": true,
    "torque_enable_ready_false": true,
    "torque_publisher_enabled_false": true,
    "control_law_changed_false": true,
    "previous_13_2b_failure_missing_contact": true,
    "derived_contact_rows_2400": true,
    "derived_contact_line_count_2401": true,
    "wbc_returncode_0": true,
    "wbc_timeout_false": true,
    "mixed_returncode_0": true,
    "mixed_timeout_false": true,
    "runner_unchanged": true,
    "wbc_runner_unchanged": true,
    "derived_swing_unchanged": true,
    "source_contact_unchanged": true,
    "mixed_total_steps_2400": true,
    "mixed_transition_count_11": true,
    "mixed_trot_FR_RL_1200": true,
    "mixed_trot_FL_RR_1200": true,
    "mixed_qp_fail_0": true,
    "mixed_saturation_0": true,
    "mixed_pass_true": true,
    "mixed_pass_margin_true": true,
    "wbc_total_steps_2400": true,
    "wbc_qp_fail_0": true,
    "wbc_saturation_0": true,
    "wbc_pass_true": true,
    "wbc_pass_margin_true": true
  },
  "threshold_checks": {
    "mixed_min_z_ge_0p22": true,
    "mixed_max_abs_roll_le_0p08": true,
    "mixed_max_abs_pitch_le_0p08": true,
    "mixed_max_joint_error_le_0p12": true,
    "mixed_max_tau_total_abs_le_23p7": true
  },
  "evidence_status": {
    "wbc_stdout": {
      "path": "/home/zanshi/robot-mpc-wbc-locomotion/results/logs_sample/stage13_2b_r1_wbc_rerun_stdout.log",
      "exists": true,
      "size": 1205,
      "sha256": "1069455f824823210b5a4bac5507e6264b4dded43cf7653eaecfb1efd221e245"
    },
    "mixed_stdout": {
      "path": "/home/zanshi/robot-mpc-wbc-locomotion/results/logs_sample/stage13_2b_r1_mixed_rerun_stdout.log",
      "exists": true,
      "size": 1478,
      "sha256": "fa88e40767f2abab255f2032bb226e2338f75ac258b94b6615ba5db473f42d94"
    },
    "derived_contact": {
      "path": "/home/zanshi/robot-mpc-wbc-locomotion/results/logs_sample/stage13_2b_r1_2400step_contact_schedule_wbc_qp.csv",
      "exists": true,
      "size": 2073480,
      "sha256": "2d612dad6063a333982128e6ce2b535060cc7cdc1b67a131e9fa9435ef268eaa"
    },
    "wbc_summary": {
      "path": "/home/zanshi/robot-mpc-wbc-locomotion/results/logs_sample/stage13_2b_r1_2400step_wbc_summary.csv",
      "exists": true,
      "size": 983,
      "sha256": "e7ec4f1742ba8538b6096c14222e80c7214ec25768e8a36ae152ae66e40bb5a0"
    },
    "wbc_log": {
      "path": "/home/zanshi/robot-mpc-wbc-locomotion/results/logs_sample/stage13_2b_r1_2400step_wbc_log.csv",
      "exists": true,
      "size": 710004,
      "sha256": "89aae719df7c06a98b53cc70938cc4ed7b5123b9d295eb879f970393e4bdf37e"
    },
    "mixed_summary": {
      "path": "/home/zanshi/robot-mpc-wbc-locomotion/results/logs_sample/stage13_2b_r1_2400step_mixed_summary.csv",
      "exists": true,
      "size": 1265,
      "sha256": "ad177850ad605fb220e4e1f55cce5c07b544d94424eab8bcc1d64a6b42c0d514"
    },
    "mixed_log": {
      "path": "/home/zanshi/robot-mpc-wbc-locomotion/results/logs_sample/stage13_2b_r1_2400step_mixed_log.csv",
      "exists": true,
      "size": 864507,
      "sha256": "772bc8db15c9a0f165ae4e690e1ffc2cf783bb8c914297551142ef119677e818"
    },
    "backup_dir": {
      "path": "/home/zanshi/robot-mpc-wbc-locomotion/results/logs_sample/stage13_2b_r1_backup",
      "exists": true,
      "size": 4096,
      "sha256": null
    }
  },
  "final_statement": "2400-step simulation-only robustness regression passed for the mixed online control baseline; no hardware deployment or actuator enablement is claimed.",
  "next_stage": "Stage 13.3 documentation consolidation and report-ready results packaging"
}